hikit/__init__.py
hikit/lando.py
hikti-0.1.dist-info/LICENSE
hikti-0.1.dist-info/METADATA
hikti-0.1.dist-info/WHEEL
hikti-0.1.dist-info/top_level.txt
hikti-0.1.dist-info/RECORD
